{"cameraMode":{"drawMode":0,"name":"Shaded","section":"Shading Mode"},"sceneLighting":false,"audioPlay":false,"sceneViewState":{"m_AlwaysRefresh":false,"showFog":true,"showSkybox":false,"showFlares":true,"showImageEffects":true,"showParticleSystems":true,"showVisualEffectGraphs":true,"m_FxEnabled":true},"in2DMode":false,"pivot":{"x":35.13999938964844,"y":1.3098089694976807,"z":19.540000915527345},"rotation":{"x":0.09193097054958344,"y":-0.23778988420963288,"z":0.02260589972138405,"w":0.9667051434516907},"size":1.5399211645126343,"orthographic":false}